MANIFEST.in
__init__.py
hello_world.py
requirements.txt
setup.py
mlfile.egg-info/PKG-INFO
mlfile.egg-info/SOURCES.txt
mlfile.egg-info/dependency_links.txt
mlfile.egg-info/entry_points.txt
mlfile.egg-info/requires.txt
mlfile.egg-info/top_level.txt